cvpackage/FaceDetectionModule.py
cvpackage/FaceMeshDetectionModule.py
cvpackage/FaceModule.py
cvpackage/HandDetectionModule.py
cvpackage/HandModule.py
cvpackage/HolisticModule.py
cvpackage/PoseDetectionModule.py
cvpackage/commonFunction.py
cvpackage/tryModules.py
cvpackage-0.0.7.dist-info/LICENSE.txt
cvpackage-0.0.7.dist-info/METADATA
cvpackage-0.0.7.dist-info/WHEEL
cvpackage-0.0.7.dist-info/top_level.txt
cvpackage-0.0.7.dist-info/RECORD
